lpsmap/version.py
lpsmap/__init__.py
lpsmap/config.py
lpsmap/ad3ext/tree.cpython-39-x86_64-linux-gnu.so
lpsmap/ad3ext/DependencyDecoder.cpp
lpsmap/ad3ext/__init__.py
lpsmap/ad3ext/sequence.cpp
lpsmap/ad3ext/tree.cpp
lpsmap/ad3ext/sequence.cpython-39-x86_64-linux-gnu.so
lpsmap/ad3qp/__init__.py
lpsmap/ad3qp/factor_graph.cpp
lpsmap/ad3qp/base.pxd
lpsmap/ad3qp/base.cpython-39-x86_64-linux-gnu.so
lpsmap/ad3qp/factor_graph.pxd
lpsmap/ad3qp/factor_graph.cpython-39-x86_64-linux-gnu.so
lpsmap/ad3qp/__init__.pxd
lpsmap/ad3qp/base.cpp
lpsmap/api/factors.py
lpsmap/api/factors_extension.py
lpsmap/api/__init__.py
lpsmap/api/api.py
lpsmap/api/autograd.py
lpsmap/core/lib/libad3.a
lpsmap/core/include/ad3/GenericFactor.h
lpsmap/core/include/ad3/FactorDense.h
lpsmap/core/include/ad3/FactorGraph.h
lpsmap/core/include/ad3/MultiVariable.h
lpsmap/core/include/ad3/Factor.h
lpsmap/core/include/ad3/Utils.h
lpsmap/tests/fw.py
lpsmap/tests/test_logic_factors.py
lpsmap/tests/__init__.py
lpsmap/tests/test_map.py
lpsmap/tests/test_basic.py
lpsmap/tests/test_torch_autograd.py
lpsmap/tests/check_logic_grad.py
lpsmap/tests/make_edge_cases.py
lp_sparsemap-1.0.dist-info/top_level.txt
lp_sparsemap-1.0.dist-info/WHEEL
lp_sparsemap-1.0.dist-info/LICENSE
lp_sparsemap-1.0.dist-info/METADATA
lp_sparsemap-1.0.dist-info/RECORD
